{"id":"791d28fe-e29b-4b01-a43f-434fe6c97ff0","timestamp":1743739021940,"matcher":{"static":{"/__nuxt_content/about/sql_dump":{"prerender":true},"/__nuxt_content/blog/sql_dump":{"prerender":true},"/__nuxt_content/work/sql_dump":{"prerender":true},"/__nuxt_content/allContent/sql_dump":{"prerender":true}},"wildcard":{},"dynamic":{}},"prerendered":["/","/music","/blog","/contact","/work","/sounddesign","/blog/foo","/blog/footnotes-to-lingering","/blog/.testing-123","/blog/bar","/work/work1-copy","/work/work1","/about"]}